<mtef><mtef generatingPlatform="Windows" generatingProduct="MathType" productVersion="6" productSubversion="7" applicationKey="DSMT6" equationOptions="1"><encodingDef encodingName="WinAllBasicCodePages" /><fontDef encDefIndex="5" fontName="Times New Roman" /><fontDef encDefIndex="3" fontName="Symbol" /><fontDef encDefIndex="5" fontName="Courier New" /><fontDef encDefIndex="4" fontName="MT Extra" /><equPrefs><sizes><size unit="points" value="12" /><size unit="percentage" value="58" /><size unit="percentage" value="42" /><size unit="percentage" value="150" /><size unit="percentage" value="100" /><size unit="percentage" value="75" /><size unit="percentage" value="150" /><size unit="points" value="1" /></sizes><sizes><spacing unit="percentage" value="150" /><spacing unit="percentage" value="150" /><spacing unit="percentage" value="100" /><spacing unit="percentage" value="45" /><spacing unit="percentage" value="25" /><spacing unit="percentage" value="8" /><spacing unit="percentage" value="25" /><spacing unit="percentage" value="100" /><spacing unit="percentage" value="100" /><spacing unit="percentage" value="35" /><spacing unit="percentage" value="100" /><spacing unit="percentage" value="8" /><spacing unit="percentage" value="5" /><spacing unit="percentage" value="2.5" /><spacing unit="percentage" value="8" /><spacing unit="percentage" value="8" /><spacing unit="percentage" value="100" /><spacing unit="percentage" value="100" /><spacing unit="percentage" value="0" /><spacing unit="percentage" value="8" /><spacing unit="percentage" value="17" /><spacing unit="percentage" value="8" /><spacing unit="percentage" value="100" /><spacing unit="percentage" value="12.5" /><spacing unit="percentage" value="45" /><spacing unit="percentage" value="5" /><spacing unit="percentage" value="5" /><spacing unit="percentage" value="5" /><spacing unit="percentage" value="5" /><spacing unit="percentage" value="10" /></sizes><styles><style fontDefIndex="1" characterStyle="0" /><style fontDefIndex="1" characterStyle="0" /><style fontDefIndex="1" characterStyle="2" /><style fontDefIndex="2" characterStyle="2" /><style fontDefIndex="2" characterStyle="0" /><style fontDefIndex="2" characterStyle="0" /><style fontDefIndex="1" characterStyle="1" /><style fontDefIndex="1" characterStyle="0" /><style fontDefIndex="3" characterStyle="0" /><style fontDefIndex="1" characterStyle="0" /><style fontDefIndex="4" characterStyle="0" /><style fontDefIndex="0" characterStyle="0" /></styles></equPrefs><full /><line><char MTCode="120" /><tmpl templateType="28"><sub /><line /><line><char MTCode="50" /></line></tmpl><full /><char MTCode="61" fontPosition="61" /><char MTCode="121" /><tmpl templateType="29"><sub /><line><char MTCode="50" /></line><line><char MTCode="51" /></line></tmpl><full /><char MTCode="61" fontPosition="61" /><tmpl templateType="28"><sub /><line /><line><char MTCode="50" /></line></tmpl><full /><char MTCode="122" /></line><end /><end /><end /><end /><end /><end /><end /><end /><end /><end /><end /><end /><end /><end /><end /><end /><end /><end /><end /><end /><end /><end /><end /><end /><end /><end /><end /><end /><end /><end /><end /><end /><end /><end /><end /><end /><end /><end /><end /><end /><end /><end /><end /><end /><end /><end /><end /><end /><end /><end /><end /><end /><end /><end /><end /><end /><end /><end /><end /><end /><end /><end /><end /><end /><end /><end /><end /><end /><end /><end /><end /><end /><end /><end /><end /><end /><end /><end /><end /><end /><end /><end /><end /><end /><end /><end /><end /><end /><end /><end /><end /><end /><end /><end /><end /><end /><end /><end /><end /><end /><end /><end /><end /><end /><end /><end /><end /><end /><end /><end /><end /><end /><end /><end /><end /><end /><end /><end /><end /><end /><end /><end /><end /><end /><end /><end /><end /><end /><end /><end /><end /><end /><end /><end /><end /><end /><end /><end /><end /><end /><end /><end /><end /><end /><end /><end /><end /><end /><end /><end /><end /><end /><end /><end /><end /><end /><end /><end /><end /><end /><end /><end /><end /><end /><end /><end /><end /><end /><end /><end /><end /><end /><end /><end /><end /><end /><end /><end /><end /><end /><end /><end /><end /><end /><end /><end /><end /><end /><end /><end /><end /><end /><end /><end /><end /><end /><end /><end /><end /><end /><end /><end /><end /><end /><end /><end /><end /><end /><end /><end /><end /><end /><end /><end /><end /><end /><end /><end /><end /><end /><end /><end /><end /><end /><end /><end /><end /><end /><end /><end /><end /><end /><end /><end /><end /><end /><end /><end /><end /><end /><end /><end /><end /><end /><end /><end /><end /><end /><end /><end /><end /><end /><end /><end /><end /><end /><end /><end /><end /><end /><end /><end /><end /><end /><end /><end /><end /><end /><end /><end /><end /><end /><end /><end /><end /><end /><end /><end /><end /><end /><end /><end /><end /><end /><end /><end /><end /><end /><end /><end /><end /><end /><end /><end /><end /><end /><end /><end /><end /><end /><end /><end /><end /><end /><end /><end /><end /><end /><end /><end /><end /><end /><end /><end /><end /><end /><end /><end /><end /><end /><end /><end /><end /><end /><end /><end /><end /><end /><end /><end /><end /><end /><end /><end /><end /><end /><end /><end /><end /><end /><end /><end /><end /><end /><end /><end /><end /><end /><end /><end /><end /><end /><end /><end /><end /><end /><end /><end /><end /><end /><end /><end /><end /><end /><end /><end /><end /><end /><end /><end /><end /><end /><end /><end /><end /><end /><end /><end /><end /><end /><end /><end /><end /><end /><end /><end /><end /><end /><end /><end /><end /><end /><end /><end /><end /><end /><end /><end /><end /><end /><end /><end /><end /><end /><end /><end /><end /><end /><end /><end /><end /><end /><end /><end /><end /><end /><end /><end /><end /><end /><end /><end /><end /><end /><end /><end /><end /><end /><end /><end /><end /><end /><end /><end /><end /><end /><end /><end /><end /><end /><end /><end /><end /><end /><end /><end /><end /><end /><end /><end /><end /><end /><end /><end /><end /><end /><end /><end /></mtef></mtef>